{
  "subject_id": "sub-309",
  "timestamp": "2026-04-01T13:45:15.521301+00:00",
  "status": "warn",
  "issues": [
    {
      "severity": "warn",
      "message": "[EO] excessive 50 Hz noise: T7, T8"
    },
    {
      "severity": "warn",
      "message": "[EC] railed channels (>1000.0 uV >10%): F5"
    },
    {
      "severity": "warn",
      "message": "[EC] excessive 50 Hz noise: T7"
    }
  ],
  "session_info": {
    "sessions": [
      "ses-1"
    ],
    "has_session_2": false
  },
  "condition_files": {
    "pre_eo": "/Volumes/LaCie/Data/EEG/Dortmund/sub-309/ses-1/eeg/sub-309_ses-1_task-EyesOpen_acq-pre_eeg.edf",
    "pre_ec": "/Volumes/LaCie/Data/EEG/Dortmund/sub-309/ses-1/eeg/sub-309_ses-1_task-EyesClosed_acq-pre_eeg.edf",
    "post_eo": "/Volumes/LaCie/Data/EEG/Dortmund/sub-309/ses-1/eeg/sub-309_ses-1_task-EyesOpen_acq-post_eeg.edf",
    "post_ec": "/Volumes/LaCie/Data/EEG/Dortmund/sub-309/ses-1/eeg/sub-309_ses-1_task-EyesClosed_acq-post_eeg.edf",
    "classification_method": "acq_entity"
  },
  "pre_eo": {
    "integrity": {
      "sfreq": 1000.0,
      "n_channels": 64,
      "duration_sec": 184.0,
      "duration_min": 3.07,
      "median_abs_amplitude_uv": 77.09
    },
    "channels": {
      "n_eeg_channels": 64,
      "present_19": [
        "Fp1",
        "Fp2",
        "F7",
        "F3",
        "Fz",
        "F4",
        "F8",
        "T3",
        "C3",
        "Cz",
        "C4",
        "T4",
        "T5",
        "P3",
        "Pz",
        "P4",
        "T6",
        "O1",
        "O2"
      ],
      "missing_19": [],
      "additional_1010": [
        "AF3",
        "AF4",
        "AF7",
        "AF8",
        "C1",
        "C2",
        "C5",
        "C6",
        "CP1",
        "CP2",
        "CP3",
        "CP4",
        "CP5",
        "CP6",
        "CPz",
        "F1",
        "F2",
        "F5",
        "F6",
        "FC1",
        "FC2",
        "FC3",
        "FC4",
        "FC5",
        "FC6",
        "FT10",
        "FT7",
        "FT8",
        "FT9",
        "Oz",
        "P1",
        "P2",
        "P5",
        "P6",
        "PO10",
        "PO3",
        "PO4",
        "PO7",
        "PO8",
        "PO9",
        "POz",
        "TP10",
        "TP7",
        "TP8",
        "TP9"
      ],
      "fcz_present": false,
      "fcz_variance_uv2": null,
      "flat_channels": [],
      "railed_channels": [],
      "noisy_50hz_channels": [
        "T7",
        "T8"
      ]
    },
    "signal_quality": {
      "median_amplitude_uv": 77.09,
      "per_channel_median_uv": {
        "Fp1": 51.31,
        "Fp2": 134.0,
        "F7": 56.92,
        "F3": 78.91,
        "Fz": 27.47,
        "F4": 21.57,
        "F8": 115.6,
        "FC5": 88.91,
        "FC1": 65.44,
        "FC2": 54.13,
        "FC6": 169.06,
        "T7": 54.65,
        "C3": 131.84,
        "Cz": 76.77,
        "C4": 28.65,
        "T8": 46.74,
        "TP9": 61.11,
        "CP5": 244.18,
        "CP1": 70.85,
        "CP2": 36.31,
        "CP6": 98.42,
        "TP10": 45.38,
        "P7": 181.07,
        "P3": 75.23,
        "Pz": 117.5,
        "P4": 164.36,
        "P8": 77.64,
        "PO9": 246.02,
        "O1": 72.42,
        "Oz": 151.87,
        "O2": 47.26,
        "PO10": 231.17,
        "AF7": 42.45,
        "AF3": 183.46,
        "AF4": 58.32,
        "AF8": 138.18,
        "F5": 238.98,
        "F1": 62.83,
        "F2": 14.66,
        "F6": 87.38,
        "FT9": 219.51,
        "FT7": 95.18,
        "FC3": 191.28,
        "FC4": 32.88,
        "FT8": 82.57,
        "FT10": 35.67,
        "C5": 29.15,
        "C1": 134.08,
        "C2": 135.28,
        "C6": 64.46,
        "TP7": 156.11,
        "CP3": 109.9,
        "CPz": 78.06,
        "CP4": 89.45,
        "TP8": 58.26,
        "P5": 41.95,
        "P1": 39.74,
        "P2": 356.33,
        "P6": 50.7,
        "PO7": 334.54,
        "PO3": 88.78,
        "POz": 64.66,
        "PO4": 92.3,
        "PO8": 172.54
      },
      "gross_artifact_pct": 0.54,
      "n_artifact_epochs": 1,
      "n_total_epochs": 184,
      "usable_duration_sec": 183.0,
      "dc_offsets_uv": {
        "Fp1": -671.87,
        "Fp2": 1287.48,
        "F7": -2693.96,
        "F3": 713.09,
        "Fz": 58.99,
        "F4": -357.89,
        "F8": 1163.15,
        "FC5": 297.35,
        "FC1": 308.43,
        "FC2": 79.89,
        "FC6": -2212.98,
        "T7": 5.72,
        "C3": 84.87,
        "Cz": -41.66,
        "C4": -1370.36,
        "T8": 249.32,
        "TP9": 271.66,
        "CP5": 1856.2,
        "CP1": 49.13,
        "CP2": -1070.81,
        "CP6": 902.36,
        "TP10": -1084.37,
        "P7": 1408.07,
        "P3": -1409.29,
        "Pz": 1685.99,
        "P4": 1161.93,
        "P8": 618.88,
        "PO9": 2294.02,
        "O1": 492.53,
        "Oz": 912.84,
        "O2": -245.73,
        "PO10": 1854.14,
        "AF7": -301.44,
        "AF3": -2430.55,
        "AF4": 451.17,
        "AF8": 78.82,
        "F5": -4136.13,
        "F1": -1145.34,
        "F2": 42.11,
        "F6": -291.89,
        "FT9": -762.0,
        "FT7": 316.87,
        "FC3": 1323.79,
        "FC4": -1020.9,
        "FT8": 767.42,
        "FT10": 198.89,
        "C5": -777.21,
        "C1": 923.56,
        "C2": 837.84,
        "C6": -1178.98,
        "TP7": 1285.44,
        "CP3": -938.83,
        "CPz": 297.03,
        "CP4": 239.48,
        "TP8": 1720.27,
        "P5": -608.44,
        "P1": -584.19,
        "P2": -3889.71,
        "P6": -1577.75,
        "PO7": 3765.05,
        "PO3": 177.73,
        "POz": -1188.88,
        "PO4": -1260.75,
        "PO8": 1650.94
      },
      "channels_with_large_offset": [
        "Fp1",
        "Fp2",
        "F7",
        "F3",
        "F4",
        "F8",
        "FC5",
        "FC1",
        "FC6",
        "C4",
        "T8",
        "TP9",
        "CP5",
        "CP2",
        "CP6",
        "TP10",
        "P7",
        "P3",
        "Pz",
        "P4",
        "P8",
        "PO9",
        "O1",
        "Oz",
        "O2",
        "PO10",
        "AF7",
        "AF3",
        "AF4",
        "F5",
        "F1",
        "F6",
        "FT9",
        "FT7",
        "FC3",
        "FC4",
        "FT8",
        "FT10",
        "C5",
        "C1",
        "C2",
        "C6",
        "TP7",
        "CP3",
        "CPz",
        "CP4",
        "TP8",
        "P5",
        "P1",
        "P2",
        "P6",
        "PO7",
        "PO3",
        "POz",
        "PO4",
        "PO8"
      ]
    },
    "markers": {
      "has_events_tsv": false,
      "n_bids_events": 0,
      "unique_event_types": [],
      "eo_duration_sec": 0.0,
      "ec_duration_sec": 0.0,
      "annotation_count": 0,
      "annotation_events": [],
      "condition_from_filename": "eo"
    }
  },
  "pre_ec": {
    "integrity": {
      "sfreq": 1000.0,
      "n_channels": 64,
      "duration_sec": 182.0,
      "duration_min": 3.03,
      "median_abs_amplitude_uv": 77.67
    },
    "channels": {
      "n_eeg_channels": 64,
      "present_19": [
        "Fp1",
        "Fp2",
        "F7",
        "F3",
        "Fz",
        "F4",
        "F8",
        "T3",
        "C3",
        "Cz",
        "C4",
        "T4",
        "T5",
        "P3",
        "Pz",
        "P4",
        "T6",
        "O1",
        "O2"
      ],
      "missing_19": [],
      "additional_1010": [
        "AF3",
        "AF4",
        "AF7",
        "AF8",
        "C1",
        "C2",
        "C5",
        "C6",
        "CP1",
        "CP2",
        "CP3",
        "CP4",
        "CP5",
        "CP6",
        "CPz",
        "F1",
        "F2",
        "F5",
        "F6",
        "FC1",
        "FC2",
        "FC3",
        "FC4",
        "FC5",
        "FC6",
        "FT10",
        "FT7",
        "FT8",
        "FT9",
        "Oz",
        "P1",
        "P2",
        "P5",
        "P6",
        "PO10",
        "PO3",
        "PO4",
        "PO7",
        "PO8",
        "PO9",
        "POz",
        "TP10",
        "TP7",
        "TP8",
        "TP9"
      ],
      "fcz_present": false,
      "fcz_variance_uv2": null,
      "flat_channels": [],
      "railed_channels": [
        "F5"
      ],
      "noisy_50hz_channels": [
        "T7"
      ]
    },
    "signal_quality": {
      "median_amplitude_uv": 77.67,
      "per_channel_median_uv": {
        "Fp1": 311.75,
        "Fp2": 87.86,
        "F7": 30.75,
        "F3": 14.42,
        "Fz": 38.54,
        "F4": 86.31,
        "F8": 132.05,
        "FC5": 17.08,
        "FC1": 38.24,
        "FC2": 19.06,
        "FC6": 321.99,
        "T7": 22.55,
        "C3": 211.06,
        "Cz": 36.05,
        "C4": 135.8,
        "T8": 25.1,
        "TP9": 30.48,
        "CP5": 214.87,
        "CP1": 24.3,
        "CP2": 173.67,
        "CP6": 82.57,
        "TP10": 131.49,
        "P7": 158.04,
        "P3": 186.75,
        "Pz": 95.51,
        "P4": 94.31,
        "P8": 88.59,
        "PO9": 248.79,
        "O1": 67.86,
        "Oz": 52.5,
        "O2": 51.62,
        "PO10": 158.45,
        "AF7": 66.78,
        "AF3": 331.61,
        "AF4": 35.79,
        "AF8": 421.65,
        "F5": 800.04,
        "F1": 141.07,
        "F2": 25.94,
        "F6": 21.33,
        "FT9": 172.3,
        "FT7": 28.95,
        "FC3": 118.37,
        "FC4": 140.32,
        "FT8": 67.42,
        "FT10": 32.77,
        "C5": 123.36,
        "C1": 67.46,
        "C2": 76.52,
        "C6": 175.99,
        "TP7": 151.0,
        "CP3": 302.97,
        "CPz": 40.5,
        "CP4": 15.61,
        "TP8": 65.63,
        "P5": 22.77,
        "P1": 90.01,
        "P2": 509.03,
        "P6": 201.48,
        "PO7": 406.11,
        "PO3": 29.3,
        "POz": 145.64,
        "PO4": 136.04,
        "PO8": 133.21
      },
      "gross_artifact_pct": 9.34,
      "n_artifact_epochs": 17,
      "n_total_epochs": 182,
      "usable_duration_sec": 165.0,
      "dc_offsets_uv": {
        "Fp1": 136.75,
        "Fp2": 1156.37,
        "F7": -2742.29,
        "F3": 566.13,
        "Fz": 251.42,
        "F4": -49.29,
        "F8": 884.56,
        "FC5": 125.07,
        "FC1": 119.74,
        "FC2": 63.01,
        "FC6": -1185.52,
        "T7": -23.42,
        "C3": 188.47,
        "Cz": -30.43,
        "C4": -1057.29,
        "T8": 164.44,
        "TP9": 195.07,
        "CP5": 869.36,
        "CP1": -29.83,
        "CP2": -653.84,
        "CP6": 517.91,
        "TP10": -906.53,
        "P7": 639.91,
        "P3": -864.74,
        "Pz": 1235.48,
        "P4": 593.69,
        "P8": 242.11,
        "PO9": 1248.67,
        "O1": 207.18,
        "Oz": 490.5,
        "O2": -270.62,
        "PO10": 920.08,
        "AF7": -113.71,
        "AF3": -1137.65,
        "AF4": 536.19,
        "AF8": -35.84,
        "F5": -1242.04,
        "F1": -557.06,
        "F2": 107.93,
        "F6": -372.34,
        "FT9": -793.19,
        "FT7": 86.96,
        "FC3": 694.61,
        "FC4": -631.16,
        "FT8": 475.1,
        "FT10": 150.77,
        "C5": -512.65,
        "C1": 501.53,
        "C2": 391.47,
        "C6": -648.98,
        "TP7": 585.05,
        "CP3": -532.05,
        "CPz": 51.98,
        "CP4": 46.35,
        "TP8": 1481.32,
        "P5": -717.31,
        "P1": -288.02,
        "P2": -2010.06,
        "P6": -979.2,
        "PO7": 2199.64,
        "PO3": 16.68,
        "POz": -708.83,
        "PO4": -881.45,
        "PO8": 970.26
      },
      "channels_with_large_offset": [
        "Fp1",
        "Fp2",
        "F7",
        "F3",
        "Fz",
        "F8",
        "FC5",
        "FC1",
        "FC6",
        "C3",
        "C4",
        "T8",
        "TP9",
        "CP5",
        "CP2",
        "CP6",
        "TP10",
        "P7",
        "P3",
        "Pz",
        "P4",
        "P8",
        "PO9",
        "O1",
        "Oz",
        "O2",
        "PO10",
        "AF7",
        "AF3",
        "AF4",
        "F5",
        "F1",
        "F2",
        "F6",
        "FT9",
        "FC3",
        "FC4",
        "FT8",
        "FT10",
        "C5",
        "C1",
        "C2",
        "C6",
        "TP7",
        "CP3",
        "TP8",
        "P5",
        "P1",
        "P2",
        "P6",
        "PO7",
        "POz",
        "PO4",
        "PO8"
      ]
    },
    "markers": {
      "has_events_tsv": false,
      "n_bids_events": 0,
      "unique_event_types": [],
      "eo_duration_sec": 0.0,
      "ec_duration_sec": 0.0,
      "annotation_count": 0,
      "annotation_events": [],
      "condition_from_filename": "ec"
    }
  },
  "channel_mapping": {
    "mapping_1020": {
      "Fp1": "Fp1",
      "Fp2": "Fp2",
      "F7": "F7",
      "F3": "F3",
      "Fz": "Fz",
      "F4": "F4",
      "F8": "F8",
      "T3": "T7",
      "C3": "C3",
      "Cz": "Cz",
      "C4": "C4",
      "T4": "T8",
      "T5": "P7",
      "P3": "P3",
      "Pz": "Pz",
      "P4": "P4",
      "T6": "P8",
      "O1": "O1",
      "O2": "O2"
    },
    "present_19": [
      "Fp1",
      "Fp2",
      "F7",
      "F3",
      "Fz",
      "F4",
      "F8",
      "T3",
      "C3",
      "Cz",
      "C4",
      "T4",
      "T5",
      "P3",
      "Pz",
      "P4",
      "T6",
      "O1",
      "O2"
    ],
    "missing_19": [],
    "additional_1010": [
      "AF3",
      "AF4",
      "AF7",
      "AF8",
      "C1",
      "C2",
      "C5",
      "C6",
      "CP1",
      "CP2",
      "CP3",
      "CP4",
      "CP5",
      "CP6",
      "CPz",
      "F1",
      "F2",
      "F5",
      "F6",
      "FC1",
      "FC2",
      "FC3",
      "FC4",
      "FC5",
      "FC6",
      "FT10",
      "FT7",
      "FT8",
      "FT9",
      "Oz",
      "P1",
      "P2",
      "P5",
      "P6",
      "PO10",
      "PO3",
      "PO4",
      "PO7",
      "PO8",
      "PO9",
      "POz",
      "TP10",
      "TP7",
      "TP8",
      "TP9"
    ]
  }
}