{
  "subject_id": "sub-027",
  "timestamp": "2026-04-01T13:42:47.615139+00:00",
  "status": "warn",
  "issues": [
    {
      "severity": "warn",
      "message": "[EO] railed channels (>1000.0 uV >10%): FC3"
    },
    {
      "severity": "warn",
      "message": "[EO] excessive 50 Hz noise: Fz, AF4"
    },
    {
      "severity": "warn",
      "message": "[EC] railed channels (>1000.0 uV >10%): PO10, AF8, FC3, PO4"
    },
    {
      "severity": "warn",
      "message": "[EC] excessive 50 Hz noise: Fz, AF4"
    }
  ],
  "session_info": {
    "sessions": [
      "ses-1"
    ],
    "has_session_2": false
  },
  "condition_files": {
    "pre_eo": "/Volumes/LaCie/Data/EEG/Dortmund/sub-027/ses-1/eeg/sub-027_ses-1_task-EyesOpen_acq-pre_eeg.edf",
    "pre_ec": "/Volumes/LaCie/Data/EEG/Dortmund/sub-027/ses-1/eeg/sub-027_ses-1_task-EyesClosed_acq-pre_eeg.edf",
    "post_eo": "/Volumes/LaCie/Data/EEG/Dortmund/sub-027/ses-1/eeg/sub-027_ses-1_task-EyesOpen_acq-post_eeg.edf",
    "post_ec": "/Volumes/LaCie/Data/EEG/Dortmund/sub-027/ses-1/eeg/sub-027_ses-1_task-EyesClosed_acq-post_eeg.edf",
    "classification_method": "acq_entity"
  },
  "pre_eo": {
    "integrity": {
      "sfreq": 1000.0,
      "n_channels": 64,
      "duration_sec": 183.0,
      "duration_min": 3.05,
      "median_abs_amplitude_uv": 51.37
    },
    "channels": {
      "n_eeg_channels": 64,
      "present_19": [
        "Fp1",
        "Fp2",
        "F7",
        "F3",
        "Fz",
        "F4",
        "F8",
        "T3",
        "C3",
        "Cz",
        "C4",
        "T4",
        "T5",
        "P3",
        "Pz",
        "P4",
        "T6",
        "O1",
        "O2"
      ],
      "missing_19": [],
      "additional_1010": [
        "AF3",
        "AF4",
        "AF7",
        "AF8",
        "C1",
        "C2",
        "C5",
        "C6",
        "CP1",
        "CP2",
        "CP3",
        "CP4",
        "CP5",
        "CP6",
        "CPz",
        "F1",
        "F2",
        "F5",
        "F6",
        "FC1",
        "FC2",
        "FC3",
        "FC4",
        "FC5",
        "FC6",
        "FT10",
        "FT7",
        "FT8",
        "FT9",
        "Oz",
        "P1",
        "P2",
        "P5",
        "P6",
        "PO10",
        "PO3",
        "PO4",
        "PO7",
        "PO8",
        "PO9",
        "POz",
        "TP10",
        "TP7",
        "TP8",
        "TP9"
      ],
      "fcz_present": false,
      "fcz_variance_uv2": null,
      "flat_channels": [],
      "railed_channels": [
        "FC3"
      ],
      "noisy_50hz_channels": [
        "Fz",
        "AF4"
      ]
    },
    "signal_quality": {
      "median_amplitude_uv": 51.37,
      "per_channel_median_uv": {
        "Fp1": 42.73,
        "Fp2": 25.82,
        "F7": 315.93,
        "F3": 48.95,
        "Fz": 66.38,
        "F4": 52.98,
        "F8": 24.09,
        "FC5": 137.79,
        "FC1": 30.96,
        "FC2": 22.58,
        "FC6": 54.23,
        "T7": 28.93,
        "C3": 37.74,
        "Cz": 245.51,
        "C4": 14.65,
        "T8": 66.06,
        "TP9": 17.0,
        "CP5": 30.86,
        "CP1": 137.72,
        "CP2": 31.96,
        "CP6": 72.44,
        "TP10": 150.17,
        "P7": 38.15,
        "P3": 19.32,
        "Pz": 44.33,
        "P4": 24.59,
        "P8": 21.08,
        "PO9": 37.82,
        "O1": 66.92,
        "Oz": 59.28,
        "O2": 101.1,
        "PO10": 116.14,
        "AF7": 157.76,
        "AF3": 252.94,
        "AF4": 83.31,
        "AF8": 247.15,
        "F5": 17.69,
        "F1": 20.74,
        "F2": 190.42,
        "F6": 120.28,
        "FT9": 30.0,
        "FT7": 43.03,
        "FC3": 910.01,
        "FC4": 65.71,
        "FT8": 30.64,
        "FT10": 22.87,
        "C5": 179.2,
        "C1": 51.41,
        "C2": 47.51,
        "C6": 53.78,
        "TP7": 64.45,
        "CP3": 59.64,
        "CPz": 231.94,
        "CP4": 46.61,
        "TP8": 60.35,
        "P5": 55.75,
        "P1": 23.36,
        "P2": 20.67,
        "P6": 29.56,
        "PO7": 57.44,
        "PO3": 20.16,
        "POz": 56.78,
        "PO4": 418.12,
        "PO8": 114.94
      },
      "gross_artifact_pct": 0.55,
      "n_artifact_epochs": 1,
      "n_total_epochs": 183,
      "usable_duration_sec": 182.0,
      "dc_offsets_uv": {
        "Fp1": -966.2,
        "Fp2": -1598.18,
        "F7": 1983.92,
        "F3": -1327.88,
        "Fz": -1128.54,
        "F4": -1032.38,
        "F8": -574.19,
        "FC5": 449.23,
        "FC1": 408.42,
        "FC2": -55.34,
        "FC6": 100.85,
        "T7": -484.42,
        "C3": -1024.77,
        "Cz": 1436.01,
        "C4": -384.91,
        "T8": -1005.52,
        "TP9": -48.06,
        "CP5": 119.39,
        "CP1": 1148.73,
        "CP2": 268.38,
        "CP6": 1335.01,
        "TP10": 1256.68,
        "P7": -696.75,
        "P3": -539.35,
        "Pz": -168.21,
        "P4": 157.11,
        "P8": -39.98,
        "PO9": -631.91,
        "O1": 1020.45,
        "Oz": 384.34,
        "O2": 548.47,
        "PO10": -3142.36,
        "AF7": -2637.25,
        "AF3": 2203.56,
        "AF4": -1378.38,
        "AF8": -6784.79,
        "F5": -92.29,
        "F1": -1040.81,
        "F2": -1918.98,
        "F6": 1825.19,
        "FT9": 80.42,
        "FT7": -1066.64,
        "FC3": -5317.56,
        "FC4": -934.8,
        "FT8": -615.4,
        "FT10": -376.02,
        "C5": 1486.64,
        "C1": 305.96,
        "C2": -76.58,
        "C6": 1006.75,
        "TP7": 652.35,
        "CP3": 61.74,
        "CPz": -1504.14,
        "CP4": 236.89,
        "TP8": 85.66,
        "P5": -872.67,
        "P1": -697.92,
        "P2": -192.1,
        "P6": 1331.04,
        "PO7": -932.93,
        "PO3": -624.2,
        "POz": 70.38,
        "PO4": -5746.6,
        "PO8": 1432.13
      },
      "channels_with_large_offset": [
        "Fp1",
        "Fp2",
        "F7",
        "F3",
        "Fz",
        "F4",
        "F8",
        "FC5",
        "FC1",
        "FC6",
        "T7",
        "C3",
        "Cz",
        "C4",
        "T8",
        "CP5",
        "CP1",
        "CP2",
        "CP6",
        "TP10",
        "P7",
        "P3",
        "Pz",
        "P4",
        "PO9",
        "O1",
        "Oz",
        "O2",
        "PO10",
        "AF7",
        "AF3",
        "AF4",
        "AF8",
        "F1",
        "F2",
        "F6",
        "FT7",
        "FC3",
        "FC4",
        "FT8",
        "FT10",
        "C5",
        "C1",
        "C6",
        "TP7",
        "CPz",
        "CP4",
        "P5",
        "P1",
        "P2",
        "P6",
        "PO7",
        "PO3",
        "PO4",
        "PO8"
      ]
    },
    "markers": {
      "has_events_tsv": false,
      "n_bids_events": 0,
      "unique_event_types": [],
      "eo_duration_sec": 0.0,
      "ec_duration_sec": 0.0,
      "annotation_count": 0,
      "annotation_events": [],
      "condition_from_filename": "eo"
    }
  },
  "pre_ec": {
    "integrity": {
      "sfreq": 1000.0,
      "n_channels": 64,
      "duration_sec": 183.0,
      "duration_min": 3.05,
      "median_abs_amplitude_uv": 69.35
    },
    "channels": {
      "n_eeg_channels": 64,
      "present_19": [
        "Fp1",
        "Fp2",
        "F7",
        "F3",
        "Fz",
        "F4",
        "F8",
        "T3",
        "C3",
        "Cz",
        "C4",
        "T4",
        "T5",
        "P3",
        "Pz",
        "P4",
        "T6",
        "O1",
        "O2"
      ],
      "missing_19": [],
      "additional_1010": [
        "AF3",
        "AF4",
        "AF7",
        "AF8",
        "C1",
        "C2",
        "C5",
        "C6",
        "CP1",
        "CP2",
        "CP3",
        "CP4",
        "CP5",
        "CP6",
        "CPz",
        "F1",
        "F2",
        "F5",
        "F6",
        "FC1",
        "FC2",
        "FC3",
        "FC4",
        "FC5",
        "FC6",
        "FT10",
        "FT7",
        "FT8",
        "FT9",
        "Oz",
        "P1",
        "P2",
        "P5",
        "P6",
        "PO10",
        "PO3",
        "PO4",
        "PO7",
        "PO8",
        "PO9",
        "POz",
        "TP10",
        "TP7",
        "TP8",
        "TP9"
      ],
      "fcz_present": false,
      "fcz_variance_uv2": null,
      "flat_channels": [],
      "railed_channels": [
        "PO10",
        "AF8",
        "FC3",
        "PO4"
      ],
      "noisy_50hz_channels": [
        "Fz",
        "AF4"
      ]
    },
    "signal_quality": {
      "median_amplitude_uv": 69.35,
      "per_channel_median_uv": {
        "Fp1": 91.06,
        "Fp2": 119.08,
        "F7": 275.25,
        "F3": 138.19,
        "Fz": 133.92,
        "F4": 87.74,
        "F8": 36.9,
        "FC5": 42.82,
        "FC1": 52.77,
        "FC2": 19.15,
        "FC6": 18.0,
        "T7": 33.59,
        "C3": 120.38,
        "Cz": 153.63,
        "C4": 55.72,
        "T8": 102.0,
        "TP9": 27.51,
        "CP5": 45.09,
        "CP1": 143.65,
        "CP2": 22.08,
        "CP6": 136.94,
        "TP10": 141.08,
        "P7": 28.73,
        "P3": 30.32,
        "Pz": 18.72,
        "P4": 23.38,
        "P8": 54.27,
        "PO9": 36.09,
        "O1": 67.62,
        "Oz": 43.11,
        "O2": 123.77,
        "PO10": 544.05,
        "AF7": 187.41,
        "AF3": 264.75,
        "AF4": 209.59,
        "AF8": 703.94,
        "F5": 19.44,
        "F1": 97.41,
        "F2": 165.94,
        "F6": 233.98,
        "FT9": 25.56,
        "FT7": 141.43,
        "FC3": 592.82,
        "FC4": 85.56,
        "FT8": 65.77,
        "FT10": 43.04,
        "C5": 151.06,
        "C1": 90.18,
        "C2": 15.2,
        "C6": 98.04,
        "TP7": 96.94,
        "CP3": 26.32,
        "CPz": 93.85,
        "CP4": 38.69,
        "TP8": 21.3,
        "P5": 52.73,
        "P1": 55.31,
        "P2": 54.8,
        "P6": 94.04,
        "PO7": 58.88,
        "PO3": 63.78,
        "POz": 22.64,
        "PO4": 674.86,
        "PO8": 145.92
      },
      "gross_artifact_pct": 5.46,
      "n_artifact_epochs": 10,
      "n_total_epochs": 183,
      "usable_duration_sec": 173.0,
      "dc_offsets_uv": {
        "Fp1": -639.93,
        "Fp2": -1216.02,
        "F7": 644.77,
        "F3": -820.88,
        "Fz": -759.58,
        "F4": -766.66,
        "F8": -450.12,
        "FC5": 15.22,
        "FC1": 178.72,
        "FC2": -211.09,
        "FC6": -141.51,
        "T7": -333.49,
        "C3": -652.15,
        "Cz": 492.44,
        "C4": -340.72,
        "T8": -740.54,
        "TP9": -158.96,
        "CP5": 234.99,
        "CP1": 412.4,
        "CP2": 81.47,
        "CP6": 824.96,
        "TP10": 505.51,
        "P7": -551.77,
        "P3": -530.63,
        "Pz": -229.19,
        "P4": 1.29,
        "P8": -16.3,
        "PO9": -479.53,
        "O1": 541.2,
        "Oz": 144.63,
        "O2": -5.64,
        "PO10": -2093.48,
        "AF7": -2073.17,
        "AF3": 1063.33,
        "AF4": -756.07,
        "AF8": -5740.43,
        "F5": -25.45,
        "F1": -816.39,
        "F2": -1221.0,
        "F6": 900.43,
        "FT9": -60.08,
        "FT7": -683.65,
        "FC3": -1950.22,
        "FC4": -705.15,
        "FT8": -531.22,
        "FT10": -409.1,
        "C5": 650.39,
        "C1": -41.28,
        "C2": -283.3,
        "C6": 611.13,
        "TP7": 237.35,
        "CP3": -240.87,
        "CPz": -546.26,
        "CP4": -85.23,
        "TP8": -198.78,
        "P5": -641.16,
        "P1": -582.25,
        "P2": -160.8,
        "P6": 939.98,
        "PO7": -681.68,
        "PO3": -621.8,
        "POz": -117.24,
        "PO4": -3375.93,
        "PO8": 514.42
      },
      "channels_with_large_offset": [
        "Fp1",
        "Fp2",
        "F7",
        "F3",
        "Fz",
        "F4",
        "F8",
        "FC1",
        "FC2",
        "FC6",
        "T7",
        "C3",
        "Cz",
        "C4",
        "T8",
        "TP9",
        "CP5",
        "CP1",
        "CP6",
        "TP10",
        "P7",
        "P3",
        "Pz",
        "PO9",
        "O1",
        "Oz",
        "PO10",
        "AF7",
        "AF3",
        "AF4",
        "AF8",
        "F1",
        "F2",
        "F6",
        "FT7",
        "FC3",
        "FC4",
        "FT8",
        "FT10",
        "C5",
        "C2",
        "C6",
        "TP7",
        "CP3",
        "CPz",
        "TP8",
        "P5",
        "P1",
        "P2",
        "P6",
        "PO7",
        "PO3",
        "POz",
        "PO4",
        "PO8"
      ]
    },
    "markers": {
      "has_events_tsv": true,
      "n_bids_events": 20,
      "unique_event_types": [
        ""
      ],
      "eo_duration_sec": 0.0,
      "ec_duration_sec": 0.0,
      "annotation_count": 0,
      "annotation_events": [],
      "condition_from_filename": "ec"
    }
  },
  "channel_mapping": {
    "mapping_1020": {
      "Fp1": "Fp1",
      "Fp2": "Fp2",
      "F7": "F7",
      "F3": "F3",
      "Fz": "Fz",
      "F4": "F4",
      "F8": "F8",
      "T3": "T7",
      "C3": "C3",
      "Cz": "Cz",
      "C4": "C4",
      "T4": "T8",
      "T5": "P7",
      "P3": "P3",
      "Pz": "Pz",
      "P4": "P4",
      "T6": "P8",
      "O1": "O1",
      "O2": "O2"
    },
    "present_19": [
      "Fp1",
      "Fp2",
      "F7",
      "F3",
      "Fz",
      "F4",
      "F8",
      "T3",
      "C3",
      "Cz",
      "C4",
      "T4",
      "T5",
      "P3",
      "Pz",
      "P4",
      "T6",
      "O1",
      "O2"
    ],
    "missing_19": [],
    "additional_1010": [
      "AF3",
      "AF4",
      "AF7",
      "AF8",
      "C1",
      "C2",
      "C5",
      "C6",
      "CP1",
      "CP2",
      "CP3",
      "CP4",
      "CP5",
      "CP6",
      "CPz",
      "F1",
      "F2",
      "F5",
      "F6",
      "FC1",
      "FC2",
      "FC3",
      "FC4",
      "FC5",
      "FC6",
      "FT10",
      "FT7",
      "FT8",
      "FT9",
      "Oz",
      "P1",
      "P2",
      "P5",
      "P6",
      "PO10",
      "PO3",
      "PO4",
      "PO7",
      "PO8",
      "PO9",
      "POz",
      "TP10",
      "TP7",
      "TP8",
      "TP9"
    ]
  }
}