{
  "subject_id": "sub-156",
  "timestamp": "2026-04-01T13:43:55.341726+00:00",
  "status": "warn",
  "issues": [
    {
      "severity": "warn",
      "message": "[EO] excessive 50 Hz noise: FC6"
    },
    {
      "severity": "warn",
      "message": "[EC] excessive 50 Hz noise: FC6"
    }
  ],
  "session_info": {
    "sessions": [
      "ses-1"
    ],
    "has_session_2": false
  },
  "condition_files": {
    "pre_eo": "/Volumes/LaCie/Data/EEG/Dortmund/sub-156/ses-1/eeg/sub-156_ses-1_task-EyesOpen_acq-pre_eeg.edf",
    "pre_ec": "/Volumes/LaCie/Data/EEG/Dortmund/sub-156/ses-1/eeg/sub-156_ses-1_task-EyesClosed_acq-pre_eeg.edf",
    "post_eo": "/Volumes/LaCie/Data/EEG/Dortmund/sub-156/ses-1/eeg/sub-156_ses-1_task-EyesOpen_acq-post_eeg.edf",
    "post_ec": "/Volumes/LaCie/Data/EEG/Dortmund/sub-156/ses-1/eeg/sub-156_ses-1_task-EyesClosed_acq-post_eeg.edf",
    "classification_method": "acq_entity"
  },
  "pre_eo": {
    "integrity": {
      "sfreq": 1000.0,
      "n_channels": 64,
      "duration_sec": 187.0,
      "duration_min": 3.12,
      "median_abs_amplitude_uv": 36.59
    },
    "channels": {
      "n_eeg_channels": 64,
      "present_19": [
        "Fp1",
        "Fp2",
        "F7",
        "F3",
        "Fz",
        "F4",
        "F8",
        "T3",
        "C3",
        "Cz",
        "C4",
        "T4",
        "T5",
        "P3",
        "Pz",
        "P4",
        "T6",
        "O1",
        "O2"
      ],
      "missing_19": [],
      "additional_1010": [
        "AF3",
        "AF4",
        "AF7",
        "AF8",
        "C1",
        "C2",
        "C5",
        "C6",
        "CP1",
        "CP2",
        "CP3",
        "CP4",
        "CP5",
        "CP6",
        "CPz",
        "F1",
        "F2",
        "F5",
        "F6",
        "FC1",
        "FC2",
        "FC3",
        "FC4",
        "FC5",
        "FC6",
        "FT10",
        "FT7",
        "FT8",
        "FT9",
        "Oz",
        "P1",
        "P2",
        "P5",
        "P6",
        "PO10",
        "PO3",
        "PO4",
        "PO7",
        "PO8",
        "PO9",
        "POz",
        "TP10",
        "TP7",
        "TP8",
        "TP9"
      ],
      "fcz_present": false,
      "fcz_variance_uv2": null,
      "flat_channels": [],
      "railed_channels": [],
      "noisy_50hz_channels": [
        "FC6"
      ]
    },
    "signal_quality": {
      "median_amplitude_uv": 36.59,
      "per_channel_median_uv": {
        "Fp1": 52.12,
        "Fp2": 91.87,
        "F7": 37.07,
        "F3": 40.13,
        "Fz": 7.61,
        "F4": 84.29,
        "F8": 43.93,
        "FC5": 17.98,
        "FC1": 5.4,
        "FC2": 97.17,
        "FC6": 133.81,
        "T7": 33.47,
        "C3": 10.16,
        "Cz": 13.47,
        "C4": 11.32,
        "T8": 120.03,
        "TP9": 50.19,
        "CP5": 13.53,
        "CP1": 21.88,
        "CP2": 45.06,
        "CP6": 24.64,
        "TP10": 30.95,
        "P7": 28.49,
        "P3": 18.05,
        "Pz": 36.42,
        "P4": 120.0,
        "P8": 54.83,
        "PO9": 99.55,
        "O1": 26.14,
        "Oz": 322.36,
        "O2": 63.59,
        "PO10": 73.39,
        "AF7": 152.44,
        "AF3": 47.32,
        "AF4": 102.14,
        "AF8": 152.02,
        "F5": 51.14,
        "F1": 9.83,
        "F2": 24.02,
        "F6": 43.06,
        "FT9": 44.2,
        "FT7": 25.51,
        "FC3": 42.03,
        "FC4": 37.98,
        "FT8": 106.01,
        "FT10": 108.84,
        "C5": 13.73,
        "C1": 35.01,
        "C2": 14.48,
        "C6": 65.88,
        "TP7": 20.65,
        "CP3": 12.73,
        "CPz": 31.65,
        "CP4": 53.94,
        "TP8": 25.24,
        "P5": 16.54,
        "P1": 154.33,
        "P2": 68.82,
        "P6": 24.71,
        "PO7": 20.02,
        "PO3": 55.62,
        "POz": 45.84,
        "PO4": 57.6,
        "PO8": 33.25
      },
      "gross_artifact_pct": 1.6,
      "n_artifact_epochs": 3,
      "n_total_epochs": 187,
      "usable_duration_sec": 184.0,
      "dc_offsets_uv": {
        "Fp1": 616.66,
        "Fp2": 1040.3,
        "F7": 47.11,
        "F3": 477.47,
        "Fz": 139.52,
        "F4": 946.73,
        "F8": -464.48,
        "FC5": -112.57,
        "FC1": 206.18,
        "FC2": -846.74,
        "FC6": -2155.79,
        "T7": -485.03,
        "C3": -45.25,
        "Cz": -77.0,
        "C4": -507.25,
        "T8": -2008.03,
        "TP9": 588.37,
        "CP5": -698.59,
        "CP1": 312.89,
        "CP2": -1169.06,
        "CP6": -830.35,
        "TP10": -488.0,
        "P7": -925.91,
        "P3": -108.66,
        "Pz": 456.97,
        "P4": -1609.95,
        "P8": 407.26,
        "PO9": -1003.06,
        "O1": -582.41,
        "Oz": -6611.12,
        "O2": -1606.68,
        "PO10": -2308.87,
        "AF7": 811.54,
        "AF3": 691.22,
        "AF4": 1384.12,
        "AF8": 1318.45,
        "F5": 480.45,
        "F1": 1003.14,
        "F2": -926.89,
        "F6": -480.41,
        "FT9": -595.72,
        "FT7": -299.6,
        "FC3": 306.54,
        "FC4": -1419.48,
        "FT8": -954.58,
        "FT10": -1338.92,
        "C5": -287.82,
        "C1": -1193.54,
        "C2": 551.42,
        "C6": -1225.77,
        "TP7": 69.29,
        "CP3": -233.38,
        "CPz": -378.18,
        "CP4": 149.06,
        "TP8": 78.69,
        "P5": -262.97,
        "P1": 909.79,
        "P2": 2592.74,
        "P6": -835.7,
        "PO7": -181.4,
        "PO3": -1354.07,
        "POz": 50.19,
        "PO4": -1559.17,
        "PO8": -142.15
      },
      "channels_with_large_offset": [
        "Fp1",
        "Fp2",
        "F3",
        "Fz",
        "F4",
        "F8",
        "FC5",
        "FC1",
        "FC2",
        "FC6",
        "T7",
        "C4",
        "T8",
        "TP9",
        "CP5",
        "CP1",
        "CP2",
        "CP6",
        "TP10",
        "P7",
        "P3",
        "Pz",
        "P4",
        "P8",
        "PO9",
        "O1",
        "Oz",
        "O2",
        "PO10",
        "AF7",
        "AF3",
        "AF4",
        "AF8",
        "F5",
        "F1",
        "F2",
        "F6",
        "FT9",
        "FT7",
        "FC3",
        "FC4",
        "FT8",
        "FT10",
        "C5",
        "C1",
        "C2",
        "C6",
        "CP3",
        "CPz",
        "CP4",
        "P5",
        "P1",
        "P2",
        "P6",
        "PO7",
        "PO3",
        "PO4",
        "PO8"
      ]
    },
    "markers": {
      "has_events_tsv": true,
      "n_bids_events": 1,
      "unique_event_types": [
        ""
      ],
      "eo_duration_sec": 0.0,
      "ec_duration_sec": 0.0,
      "annotation_count": 0,
      "annotation_events": [],
      "condition_from_filename": "eo"
    }
  },
  "pre_ec": {
    "integrity": {
      "sfreq": 1000.0,
      "n_channels": 64,
      "duration_sec": 192.0,
      "duration_min": 3.2,
      "median_abs_amplitude_uv": 41.32
    },
    "channels": {
      "n_eeg_channels": 64,
      "present_19": [
        "Fp1",
        "Fp2",
        "F7",
        "F3",
        "Fz",
        "F4",
        "F8",
        "T3",
        "C3",
        "Cz",
        "C4",
        "T4",
        "T5",
        "P3",
        "Pz",
        "P4",
        "T6",
        "O1",
        "O2"
      ],
      "missing_19": [],
      "additional_1010": [
        "AF3",
        "AF4",
        "AF7",
        "AF8",
        "C1",
        "C2",
        "C5",
        "C6",
        "CP1",
        "CP2",
        "CP3",
        "CP4",
        "CP5",
        "CP6",
        "CPz",
        "F1",
        "F2",
        "F5",
        "F6",
        "FC1",
        "FC2",
        "FC3",
        "FC4",
        "FC5",
        "FC6",
        "FT10",
        "FT7",
        "FT8",
        "FT9",
        "Oz",
        "P1",
        "P2",
        "P5",
        "P6",
        "PO10",
        "PO3",
        "PO4",
        "PO7",
        "PO8",
        "PO9",
        "POz",
        "TP10",
        "TP7",
        "TP8",
        "TP9"
      ],
      "fcz_present": false,
      "fcz_variance_uv2": null,
      "flat_channels": [],
      "railed_channels": [],
      "noisy_50hz_channels": [
        "FC6"
      ]
    },
    "signal_quality": {
      "median_amplitude_uv": 41.32,
      "per_channel_median_uv": {
        "Fp1": 75.79,
        "Fp2": 119.51,
        "F7": 31.44,
        "F3": 56.34,
        "Fz": 18.36,
        "F4": 69.38,
        "F8": 49.38,
        "FC5": 28.25,
        "FC1": 18.54,
        "FC2": 71.12,
        "FC6": 131.08,
        "T7": 35.19,
        "C3": 17.65,
        "Cz": 23.42,
        "C4": 33.24,
        "T8": 111.29,
        "TP9": 85.19,
        "CP5": 16.09,
        "CP1": 29.07,
        "CP2": 81.62,
        "CP6": 23.59,
        "TP10": 22.47,
        "P7": 36.37,
        "P3": 18.35,
        "Pz": 37.97,
        "P4": 125.54,
        "P8": 48.39,
        "PO9": 87.44,
        "O1": 24.92,
        "Oz": 417.64,
        "O2": 119.03,
        "PO10": 108.38,
        "AF7": 110.46,
        "AF3": 83.75,
        "AF4": 105.72,
        "AF8": 134.77,
        "F5": 29.19,
        "F1": 70.78,
        "F2": 35.37,
        "F6": 47.53,
        "FT9": 37.42,
        "FT7": 29.41,
        "FC3": 31.52,
        "FC4": 70.36,
        "FT8": 62.98,
        "FT10": 69.58,
        "C5": 20.17,
        "C1": 64.05,
        "C2": 21.02,
        "C6": 78.85,
        "TP7": 31.54,
        "CP3": 15.88,
        "CPz": 30.42,
        "CP4": 15.9,
        "TP8": 28.2,
        "P5": 17.82,
        "P1": 23.81,
        "P2": 154.07,
        "P6": 30.23,
        "PO7": 20.43,
        "PO3": 83.35,
        "POz": 26.23,
        "PO4": 114.45,
        "PO8": 23.37
      },
      "gross_artifact_pct": 0.52,
      "n_artifact_epochs": 1,
      "n_total_epochs": 192,
      "usable_duration_sec": 191.0,
      "dc_offsets_uv": {
        "Fp1": 471.29,
        "Fp2": 537.04,
        "F7": -31.52,
        "F3": 334.32,
        "Fz": 157.58,
        "F4": 704.1,
        "F8": -137.14,
        "FC5": -14.77,
        "FC1": 233.0,
        "FC2": -434.56,
        "FC6": -1501.03,
        "T7": -350.28,
        "C3": -18.62,
        "Cz": -10.47,
        "C4": -434.74,
        "T8": -1457.26,
        "TP9": 253.21,
        "CP5": -730.53,
        "CP1": 202.38,
        "CP2": -863.55,
        "CP6": -872.13,
        "TP10": -468.55,
        "P7": -847.38,
        "P3": -154.83,
        "Pz": 287.06,
        "P4": -950.12,
        "P8": 108.39,
        "PO9": -637.48,
        "O1": -499.58,
        "Oz": -4945.65,
        "O2": -1194.54,
        "PO10": -1807.65,
        "AF7": 374.57,
        "AF3": 531.24,
        "AF4": 1125.2,
        "AF8": 943.85,
        "F5": 734.25,
        "F1": 906.29,
        "F2": -742.41,
        "F6": -157.49,
        "FT9": -396.98,
        "FT7": -188.66,
        "FC3": 192.0,
        "FC4": -1134.94,
        "FT8": -505.56,
        "FT10": -867.95,
        "C5": -265.72,
        "C1": -922.11,
        "C2": 637.39,
        "C6": -904.67,
        "TP7": -62.41,
        "CP3": -236.94,
        "CPz": -231.52,
        "CP4": -15.98,
        "TP8": -67.22,
        "P5": -287.86,
        "P1": 646.23,
        "P2": 2159.85,
        "P6": -853.22,
        "PO7": -251.36,
        "PO3": -1059.29,
        "POz": -156.18,
        "PO4": -1176.92,
        "PO8": -222.93
      },
      "channels_with_large_offset": [
        "Fp1",
        "Fp2",
        "F3",
        "Fz",
        "F4",
        "F8",
        "FC1",
        "FC2",
        "FC6",
        "T7",
        "C4",
        "T8",
        "TP9",
        "CP5",
        "CP1",
        "CP2",
        "CP6",
        "TP10",
        "P7",
        "P3",
        "Pz",
        "P4",
        "P8",
        "PO9",
        "O1",
        "Oz",
        "O2",
        "PO10",
        "AF7",
        "AF3",
        "AF4",
        "AF8",
        "F5",
        "F1",
        "F2",
        "F6",
        "FT9",
        "FT7",
        "FC3",
        "FC4",
        "FT8",
        "FT10",
        "C5",
        "C1",
        "C2",
        "C6",
        "CP3",
        "CPz",
        "P5",
        "P1",
        "P2",
        "P6",
        "PO7",
        "PO3",
        "POz",
        "PO4",
        "PO8"
      ]
    },
    "markers": {
      "has_events_tsv": true,
      "n_bids_events": 1,
      "unique_event_types": [
        ""
      ],
      "eo_duration_sec": 0.0,
      "ec_duration_sec": 0.0,
      "annotation_count": 0,
      "annotation_events": [],
      "condition_from_filename": "ec"
    }
  },
  "channel_mapping": {
    "mapping_1020": {
      "Fp1": "Fp1",
      "Fp2": "Fp2",
      "F7": "F7",
      "F3": "F3",
      "Fz": "Fz",
      "F4": "F4",
      "F8": "F8",
      "T3": "T7",
      "C3": "C3",
      "Cz": "Cz",
      "C4": "C4",
      "T4": "T8",
      "T5": "P7",
      "P3": "P3",
      "Pz": "Pz",
      "P4": "P4",
      "T6": "P8",
      "O1": "O1",
      "O2": "O2"
    },
    "present_19": [
      "Fp1",
      "Fp2",
      "F7",
      "F3",
      "Fz",
      "F4",
      "F8",
      "T3",
      "C3",
      "Cz",
      "C4",
      "T4",
      "T5",
      "P3",
      "Pz",
      "P4",
      "T6",
      "O1",
      "O2"
    ],
    "missing_19": [],
    "additional_1010": [
      "AF3",
      "AF4",
      "AF7",
      "AF8",
      "C1",
      "C2",
      "C5",
      "C6",
      "CP1",
      "CP2",
      "CP3",
      "CP4",
      "CP5",
      "CP6",
      "CPz",
      "F1",
      "F2",
      "F5",
      "F6",
      "FC1",
      "FC2",
      "FC3",
      "FC4",
      "FC5",
      "FC6",
      "FT10",
      "FT7",
      "FT8",
      "FT9",
      "Oz",
      "P1",
      "P2",
      "P5",
      "P6",
      "PO10",
      "PO3",
      "PO4",
      "PO7",
      "PO8",
      "PO9",
      "POz",
      "TP10",
      "TP7",
      "TP8",
      "TP9"
    ]
  }
}