{
  "subject_id": "sub-297",
  "timestamp": "2026-04-01T13:45:09.639401+00:00",
  "status": "warn",
  "issues": [
    {
      "severity": "warn",
      "message": "[EO] gross artifact=20.7%, exceeds 20.0%"
    },
    {
      "severity": "warn",
      "message": "[EC] railed channels (>1000.0 uV >10%): FT9"
    }
  ],
  "session_info": {
    "sessions": [
      "ses-1"
    ],
    "has_session_2": false
  },
  "condition_files": {
    "pre_eo": "/Volumes/LaCie/Data/EEG/Dortmund/sub-297/ses-1/eeg/sub-297_ses-1_task-EyesOpen_acq-pre_eeg.edf",
    "pre_ec": "/Volumes/LaCie/Data/EEG/Dortmund/sub-297/ses-1/eeg/sub-297_ses-1_task-EyesClosed_acq-pre_eeg.edf",
    "post_eo": "/Volumes/LaCie/Data/EEG/Dortmund/sub-297/ses-1/eeg/sub-297_ses-1_task-EyesOpen_acq-post_eeg.edf",
    "post_ec": "/Volumes/LaCie/Data/EEG/Dortmund/sub-297/ses-1/eeg/sub-297_ses-1_task-EyesClosed_acq-post_eeg.edf",
    "classification_method": "acq_entity"
  },
  "pre_eo": {
    "integrity": {
      "sfreq": 1000.0,
      "n_channels": 64,
      "duration_sec": 188.0,
      "duration_min": 3.13,
      "median_abs_amplitude_uv": 91.27
    },
    "channels": {
      "n_eeg_channels": 64,
      "present_19": [
        "Fp1",
        "Fp2",
        "F7",
        "F3",
        "Fz",
        "F4",
        "F8",
        "T3",
        "C3",
        "Cz",
        "C4",
        "T4",
        "T5",
        "P3",
        "Pz",
        "P4",
        "T6",
        "O1",
        "O2"
      ],
      "missing_19": [],
      "additional_1010": [
        "AF3",
        "AF4",
        "AF7",
        "AF8",
        "C1",
        "C2",
        "C5",
        "C6",
        "CP1",
        "CP2",
        "CP3",
        "CP4",
        "CP5",
        "CP6",
        "CPz",
        "F1",
        "F2",
        "F5",
        "F6",
        "FC1",
        "FC2",
        "FC3",
        "FC4",
        "FC5",
        "FC6",
        "FT10",
        "FT7",
        "FT8",
        "FT9",
        "Oz",
        "P1",
        "P2",
        "P5",
        "P6",
        "PO10",
        "PO3",
        "PO4",
        "PO7",
        "PO8",
        "PO9",
        "POz",
        "TP10",
        "TP7",
        "TP8",
        "TP9"
      ],
      "fcz_present": false,
      "fcz_variance_uv2": null,
      "flat_channels": [],
      "railed_channels": [],
      "noisy_50hz_channels": []
    },
    "signal_quality": {
      "median_amplitude_uv": 91.27,
      "per_channel_median_uv": {
        "Fp1": 46.81,
        "Fp2": 78.51,
        "F7": 171.22,
        "F3": 113.79,
        "Fz": 108.88,
        "F4": 106.51,
        "F8": 85.03,
        "FC5": 33.25,
        "FC1": 131.8,
        "FC2": 29.64,
        "FC6": 157.43,
        "T7": 76.17,
        "C3": 80.16,
        "Cz": 171.53,
        "C4": 225.68,
        "T8": 76.7,
        "TP9": 400.19,
        "CP5": 111.77,
        "CP1": 134.54,
        "CP2": 139.07,
        "CP6": 134.36,
        "TP10": 55.93,
        "P7": 107.33,
        "P3": 62.23,
        "Pz": 110.76,
        "P4": 112.29,
        "P8": 54.7,
        "PO9": 160.88,
        "O1": 286.1,
        "Oz": 171.54,
        "O2": 138.66,
        "PO10": 34.95,
        "AF7": 29.3,
        "AF3": 108.5,
        "AF4": 78.52,
        "AF8": 20.0,
        "F5": 44.36,
        "F1": 86.95,
        "F2": 53.23,
        "F6": 116.25,
        "FT9": 265.93,
        "FT7": 49.87,
        "FC3": 97.57,
        "FC4": 124.25,
        "FT8": 105.9,
        "FT10": 27.79,
        "C5": 61.76,
        "C1": 83.36,
        "C2": 87.11,
        "C6": 78.44,
        "TP7": 178.89,
        "CP3": 88.24,
        "CPz": 107.7,
        "CP4": 100.65,
        "TP8": 181.73,
        "P5": 84.94,
        "P1": 52.06,
        "P2": 131.7,
        "P6": 111.4,
        "PO7": 174.89,
        "PO3": 92.38,
        "POz": 162.4,
        "PO4": 148.75,
        "PO8": 132.48
      },
      "gross_artifact_pct": 20.74,
      "n_artifact_epochs": 39,
      "n_total_epochs": 188,
      "usable_duration_sec": 149.0,
      "dc_offsets_uv": {
        "Fp1": 503.88,
        "Fp2": 35.46,
        "F7": -551.87,
        "F3": -421.16,
        "Fz": -374.31,
        "F4": -234.47,
        "F8": 1011.03,
        "FC5": 604.21,
        "FC1": -416.22,
        "FC2": 446.13,
        "FC6": -1445.84,
        "T7": -84.4,
        "C3": -122.39,
        "Cz": -1544.63,
        "C4": -1838.24,
        "T8": -606.74,
        "TP9": -2930.22,
        "CP5": -501.28,
        "CP1": -381.41,
        "CP2": -495.51,
        "CP6": -1369.16,
        "TP10": -137.45,
        "P7": -780.19,
        "P3": 125.78,
        "Pz": -123.78,
        "P4": -528.69,
        "P8": -642.67,
        "PO9": -1285.8,
        "O1": -2793.61,
        "Oz": -648.43,
        "O2": -1002.91,
        "PO10": 412.97,
        "AF7": 491.77,
        "AF3": 1686.61,
        "AF4": -270.41,
        "AF8": 803.48,
        "F5": 859.4,
        "F1": -388.97,
        "F2": 255.35,
        "F6": 1786.79,
        "FT9": -7155.02,
        "FT7": 364.75,
        "FC3": -160.81,
        "FC4": -324.7,
        "FT8": -523.33,
        "FT10": 957.3,
        "C5": -128.73,
        "C1": 1695.26,
        "C2": 151.03,
        "C6": -246.05,
        "TP7": -772.49,
        "CP3": -54.81,
        "CPz": -337.7,
        "CP4": -146.75,
        "TP8": -1062.68,
        "P5": -458.03,
        "P1": 1276.94,
        "P2": -584.31,
        "P6": -218.53,
        "PO7": -1956.59,
        "PO3": -101.73,
        "POz": -636.36,
        "PO4": -1169.27,
        "PO8": -771.93
      },
      "channels_with_large_offset": [
        "Fp1",
        "F7",
        "F3",
        "Fz",
        "F4",
        "F8",
        "FC5",
        "FC1",
        "FC2",
        "FC6",
        "C3",
        "Cz",
        "C4",
        "T8",
        "TP9",
        "CP5",
        "CP1",
        "CP2",
        "CP6",
        "TP10",
        "P7",
        "P3",
        "Pz",
        "P4",
        "P8",
        "PO9",
        "O1",
        "Oz",
        "O2",
        "PO10",
        "AF7",
        "AF3",
        "AF4",
        "AF8",
        "F5",
        "F1",
        "F2",
        "F6",
        "FT9",
        "FT7",
        "FC3",
        "FC4",
        "FT8",
        "FT10",
        "C5",
        "C1",
        "C2",
        "C6",
        "TP7",
        "CPz",
        "CP4",
        "TP8",
        "P5",
        "P1",
        "P2",
        "P6",
        "PO7",
        "PO3",
        "POz",
        "PO4",
        "PO8"
      ]
    },
    "markers": {
      "has_events_tsv": false,
      "n_bids_events": 0,
      "unique_event_types": [],
      "eo_duration_sec": 0.0,
      "ec_duration_sec": 0.0,
      "annotation_count": 0,
      "annotation_events": [],
      "condition_from_filename": "eo"
    }
  },
  "pre_ec": {
    "integrity": {
      "sfreq": 1000.0,
      "n_channels": 64,
      "duration_sec": 185.0,
      "duration_min": 3.08,
      "median_abs_amplitude_uv": 50.39
    },
    "channels": {
      "n_eeg_channels": 64,
      "present_19": [
        "Fp1",
        "Fp2",
        "F7",
        "F3",
        "Fz",
        "F4",
        "F8",
        "T3",
        "C3",
        "Cz",
        "C4",
        "T4",
        "T5",
        "P3",
        "Pz",
        "P4",
        "T6",
        "O1",
        "O2"
      ],
      "missing_19": [],
      "additional_1010": [
        "AF3",
        "AF4",
        "AF7",
        "AF8",
        "C1",
        "C2",
        "C5",
        "C6",
        "CP1",
        "CP2",
        "CP3",
        "CP4",
        "CP5",
        "CP6",
        "CPz",
        "F1",
        "F2",
        "F5",
        "F6",
        "FC1",
        "FC2",
        "FC3",
        "FC4",
        "FC5",
        "FC6",
        "FT10",
        "FT7",
        "FT8",
        "FT9",
        "Oz",
        "P1",
        "P2",
        "P5",
        "P6",
        "PO10",
        "PO3",
        "PO4",
        "PO7",
        "PO8",
        "PO9",
        "POz",
        "TP10",
        "TP7",
        "TP8",
        "TP9"
      ],
      "fcz_present": false,
      "fcz_variance_uv2": null,
      "flat_channels": [],
      "railed_channels": [
        "FT9"
      ],
      "noisy_50hz_channels": []
    },
    "signal_quality": {
      "median_amplitude_uv": 50.39,
      "per_channel_median_uv": {
        "Fp1": 41.4,
        "Fp2": 37.03,
        "F7": 60.56,
        "F3": 22.8,
        "Fz": 52.52,
        "F4": 25.2,
        "F8": 91.51,
        "FC5": 69.46,
        "FC1": 17.48,
        "FC2": 49.16,
        "FC6": 141.55,
        "T7": 20.32,
        "C3": 24.07,
        "Cz": 129.47,
        "C4": 236.89,
        "T8": 69.52,
        "TP9": 263.65,
        "CP5": 70.18,
        "CP1": 25.8,
        "CP2": 26.13,
        "CP6": 168.92,
        "TP10": 50.2,
        "P7": 90.53,
        "P3": 25.56,
        "Pz": 28.64,
        "P4": 44.17,
        "P8": 59.03,
        "PO9": 182.84,
        "O1": 282.82,
        "Oz": 42.25,
        "O2": 102.7,
        "PO10": 56.43,
        "AF7": 42.74,
        "AF3": 189.08,
        "AF4": 27.59,
        "AF8": 100.77,
        "F5": 101.54,
        "F1": 49.55,
        "F2": 40.12,
        "F6": 159.88,
        "FT9": 747.93,
        "FT7": 30.79,
        "FC3": 19.26,
        "FC4": 18.01,
        "FT8": 48.04,
        "FT10": 104.52,
        "C5": 30.93,
        "C1": 135.1,
        "C2": 25.38,
        "C6": 34.85,
        "TP7": 48.59,
        "CP3": 21.71,
        "CPz": 42.51,
        "CP4": 22.72,
        "TP8": 86.82,
        "P5": 17.94,
        "P1": 173.47,
        "P2": 44.61,
        "P6": 20.99,
        "PO7": 134.69,
        "PO3": 20.71,
        "POz": 32.33,
        "PO4": 118.54,
        "PO8": 32.91
      },
      "gross_artifact_pct": 0.54,
      "n_artifact_epochs": 1,
      "n_total_epochs": 185,
      "usable_duration_sec": 184.0,
      "dc_offsets_uv": {
        "Fp1": 684.93,
        "Fp2": 441.45,
        "F7": 45.64,
        "F3": -75.79,
        "Fz": 73.97,
        "F4": 73.67,
        "F8": 572.58,
        "FC5": 440.47,
        "FC1": -4.07,
        "FC2": 401.87,
        "FC6": -809.37,
        "T7": 99.41,
        "C3": 76.48,
        "Cz": -839.98,
        "C4": -771.98,
        "T8": -302.52,
        "TP9": -1390.11,
        "CP5": -160.2,
        "CP1": 9.7,
        "CP2": -121.6,
        "CP6": -680.0,
        "TP10": -105.69,
        "P7": -244.12,
        "P3": 244.87,
        "Pz": 114.42,
        "P4": -134.78,
        "P8": -383.09,
        "PO9": -569.9,
        "O1": -1528.24,
        "Oz": -155.23,
        "O2": -422.83,
        "PO10": 383.1,
        "AF7": 514.25,
        "AF3": 1091.63,
        "AF4": 77.03,
        "AF8": 598.8,
        "F5": 675.41,
        "F1": 49.06,
        "F2": 321.66,
        "F6": 1284.11,
        "FT9": -5131.09,
        "FT7": 430.77,
        "FC3": 42.67,
        "FC4": -74.08,
        "FT8": -128.96,
        "FT10": 628.1,
        "C5": -205.55,
        "C1": 719.86,
        "C2": 306.68,
        "C6": -12.06,
        "TP7": -311.36,
        "CP3": 96.78,
        "CPz": -16.49,
        "CP4": 52.66,
        "TP8": -488.65,
        "P5": -289.15,
        "P1": 946.94,
        "P2": -155.79,
        "P6": 28.45,
        "PO7": -1391.79,
        "PO3": 122.36,
        "POz": -140.28,
        "PO4": -524.41,
        "PO8": -281.87
      },
      "channels_with_large_offset": [
        "Fp1",
        "Fp2",
        "F8",
        "FC5",
        "FC2",
        "FC6",
        "Cz",
        "C4",
        "T8",
        "TP9",
        "CP5",
        "CP2",
        "CP6",
        "TP10",
        "P7",
        "P3",
        "Pz",
        "P4",
        "P8",
        "PO9",
        "O1",
        "Oz",
        "O2",
        "PO10",
        "AF7",
        "AF3",
        "AF8",
        "F5",
        "F2",
        "F6",
        "FT9",
        "FT7",
        "FT8",
        "FT10",
        "C5",
        "C1",
        "C2",
        "TP7",
        "TP8",
        "P5",
        "P1",
        "P2",
        "PO7",
        "PO3",
        "POz",
        "PO4",
        "PO8"
      ]
    },
    "markers": {
      "has_events_tsv": false,
      "n_bids_events": 0,
      "unique_event_types": [],
      "eo_duration_sec": 0.0,
      "ec_duration_sec": 0.0,
      "annotation_count": 0,
      "annotation_events": [],
      "condition_from_filename": "ec"
    }
  },
  "channel_mapping": {
    "mapping_1020": {
      "Fp1": "Fp1",
      "Fp2": "Fp2",
      "F7": "F7",
      "F3": "F3",
      "Fz": "Fz",
      "F4": "F4",
      "F8": "F8",
      "T3": "T7",
      "C3": "C3",
      "Cz": "Cz",
      "C4": "C4",
      "T4": "T8",
      "T5": "P7",
      "P3": "P3",
      "Pz": "Pz",
      "P4": "P4",
      "T6": "P8",
      "O1": "O1",
      "O2": "O2"
    },
    "present_19": [
      "Fp1",
      "Fp2",
      "F7",
      "F3",
      "Fz",
      "F4",
      "F8",
      "T3",
      "C3",
      "Cz",
      "C4",
      "T4",
      "T5",
      "P3",
      "Pz",
      "P4",
      "T6",
      "O1",
      "O2"
    ],
    "missing_19": [],
    "additional_1010": [
      "AF3",
      "AF4",
      "AF7",
      "AF8",
      "C1",
      "C2",
      "C5",
      "C6",
      "CP1",
      "CP2",
      "CP3",
      "CP4",
      "CP5",
      "CP6",
      "CPz",
      "F1",
      "F2",
      "F5",
      "F6",
      "FC1",
      "FC2",
      "FC3",
      "FC4",
      "FC5",
      "FC6",
      "FT10",
      "FT7",
      "FT8",
      "FT9",
      "Oz",
      "P1",
      "P2",
      "P5",
      "P6",
      "PO10",
      "PO3",
      "PO4",
      "PO7",
      "PO8",
      "PO9",
      "POz",
      "TP10",
      "TP7",
      "TP8",
      "TP9"
    ]
  }
}