{
  "subject_id": "sub-504",
  "timestamp": "2026-04-01T13:46:49.712055+00:00",
  "status": "warn",
  "issues": [
    {
      "severity": "warn",
      "message": "[EC] railed channels (>1000.0 uV >10%): TP9"
    }
  ],
  "session_info": {
    "sessions": [
      "ses-1"
    ],
    "has_session_2": false
  },
  "condition_files": {
    "pre_eo": "/Volumes/LaCie/Data/EEG/Dortmund/sub-504/ses-1/eeg/sub-504_ses-1_task-EyesOpen_acq-pre_eeg.edf",
    "pre_ec": "/Volumes/LaCie/Data/EEG/Dortmund/sub-504/ses-1/eeg/sub-504_ses-1_task-EyesClosed_acq-pre_eeg.edf",
    "post_eo": "/Volumes/LaCie/Data/EEG/Dortmund/sub-504/ses-1/eeg/sub-504_ses-1_task-EyesOpen_acq-post_eeg.edf",
    "post_ec": "/Volumes/LaCie/Data/EEG/Dortmund/sub-504/ses-1/eeg/sub-504_ses-1_task-EyesClosed_acq-post_eeg.edf",
    "classification_method": "acq_entity"
  },
  "pre_eo": {
    "integrity": {
      "sfreq": 1000.0,
      "n_channels": 64,
      "duration_sec": 192.0,
      "duration_min": 3.2,
      "median_abs_amplitude_uv": 50.45
    },
    "channels": {
      "n_eeg_channels": 64,
      "present_19": [
        "Fp1",
        "Fp2",
        "F7",
        "F3",
        "Fz",
        "F4",
        "F8",
        "T3",
        "C3",
        "Cz",
        "C4",
        "T4",
        "T5",
        "P3",
        "Pz",
        "P4",
        "T6",
        "O1",
        "O2"
      ],
      "missing_19": [],
      "additional_1010": [
        "AF3",
        "AF4",
        "AF7",
        "AF8",
        "C1",
        "C2",
        "C5",
        "C6",
        "CP1",
        "CP2",
        "CP3",
        "CP4",
        "CP5",
        "CP6",
        "CPz",
        "F1",
        "F2",
        "F5",
        "F6",
        "FC1",
        "FC2",
        "FC3",
        "FC4",
        "FC5",
        "FC6",
        "FT10",
        "FT7",
        "FT8",
        "FT9",
        "Oz",
        "P1",
        "P2",
        "P5",
        "P6",
        "PO10",
        "PO3",
        "PO4",
        "PO7",
        "PO8",
        "PO9",
        "POz",
        "TP10",
        "TP7",
        "TP8",
        "TP9"
      ],
      "fcz_present": false,
      "fcz_variance_uv2": null,
      "flat_channels": [],
      "railed_channels": [],
      "noisy_50hz_channels": []
    },
    "signal_quality": {
      "median_amplitude_uv": 50.45,
      "per_channel_median_uv": {
        "Fp1": 31.6,
        "Fp2": 120.98,
        "F7": 99.71,
        "F3": 25.47,
        "Fz": 48.44,
        "F4": 22.19,
        "F8": 42.88,
        "FC5": 93.65,
        "FC1": 26.68,
        "FC2": 126.7,
        "FC6": 20.21,
        "T7": 34.21,
        "C3": 65.95,
        "Cz": 35.79,
        "C4": 41.28,
        "T8": 18.23,
        "TP9": 241.91,
        "CP5": 137.73,
        "CP1": 80.77,
        "CP2": 104.68,
        "CP6": 116.4,
        "TP10": 56.99,
        "P7": 100.22,
        "P3": 25.31,
        "Pz": 57.35,
        "P4": 170.39,
        "P8": 102.1,
        "PO9": 31.61,
        "O1": 35.69,
        "Oz": 23.76,
        "O2": 26.06,
        "PO10": 15.97,
        "AF7": 48.63,
        "AF3": 63.78,
        "AF4": 19.58,
        "AF8": 323.66,
        "F5": 23.92,
        "F1": 45.87,
        "F2": 58.83,
        "F6": 66.42,
        "FT9": 98.23,
        "FT7": 24.52,
        "FC3": 86.75,
        "FC4": 93.9,
        "FT8": 82.12,
        "FT10": 27.53,
        "C5": 67.73,
        "C1": 94.74,
        "C2": 64.69,
        "C6": 106.23,
        "TP7": 144.19,
        "CP3": 36.11,
        "CPz": 75.04,
        "CP4": 10.39,
        "TP8": 73.52,
        "P5": 165.34,
        "P1": 122.65,
        "P2": 15.41,
        "P6": 84.54,
        "PO7": 26.76,
        "PO3": 23.71,
        "POz": 25.37,
        "PO4": 42.74,
        "PO8": 134.74
      },
      "gross_artifact_pct": 0.52,
      "n_artifact_epochs": 1,
      "n_total_epochs": 192,
      "usable_duration_sec": 191.0,
      "dc_offsets_uv": {
        "Fp1": -427.37,
        "Fp2": 321.96,
        "F7": -217.29,
        "F3": -797.96,
        "Fz": -1121.56,
        "F4": 579.67,
        "F8": -1128.87,
        "FC5": -1147.62,
        "FC1": -238.8,
        "FC2": 1216.83,
        "FC6": -625.27,
        "T7": -857.29,
        "C3": -820.56,
        "Cz": -656.68,
        "C4": 804.23,
        "T8": -695.73,
        "TP9": -1165.12,
        "CP5": -1322.74,
        "CP1": -974.2,
        "CP2": -1506.73,
        "CP6": -1271.43,
        "TP10": -1208.98,
        "P7": -682.79,
        "P3": -425.68,
        "Pz": -1327.18,
        "P4": 1132.14,
        "P8": -1799.06,
        "PO9": -407.13,
        "O1": -1264.65,
        "Oz": 200.26,
        "O2": -194.97,
        "PO10": -317.01,
        "AF7": -1088.88,
        "AF3": 285.81,
        "AF4": -199.91,
        "AF8": 1425.17,
        "F5": -115.41,
        "F1": -247.09,
        "F2": -501.65,
        "F6": -21.93,
        "FT9": -1036.3,
        "FT7": -1156.45,
        "FC3": -1119.22,
        "FC4": 1044.37,
        "FT8": -1253.66,
        "FT10": -137.97,
        "C5": -929.72,
        "C1": 277.24,
        "C2": -848.85,
        "C6": -1047.26,
        "TP7": -2612.67,
        "CP3": -913.9,
        "CPz": 971.07,
        "CP4": -35.38,
        "TP8": 111.49,
        "P5": 2040.82,
        "P1": 1611.69,
        "P2": -760.95,
        "P6": 472.03,
        "PO7": -571.73,
        "PO3": -605.24,
        "POz": -329.4,
        "PO4": 31.78,
        "PO8": 1747.28
      },
      "channels_with_large_offset": [
        "Fp1",
        "Fp2",
        "F7",
        "F3",
        "Fz",
        "F4",
        "F8",
        "FC5",
        "FC1",
        "FC2",
        "FC6",
        "T7",
        "C3",
        "Cz",
        "C4",
        "T8",
        "TP9",
        "CP5",
        "CP1",
        "CP2",
        "CP6",
        "TP10",
        "P7",
        "P3",
        "Pz",
        "P4",
        "P8",
        "PO9",
        "O1",
        "Oz",
        "O2",
        "PO10",
        "AF7",
        "AF3",
        "AF4",
        "AF8",
        "F5",
        "F1",
        "F2",
        "FT9",
        "FT7",
        "FC3",
        "FC4",
        "FT8",
        "FT10",
        "C5",
        "C1",
        "C2",
        "C6",
        "TP7",
        "CP3",
        "CPz",
        "TP8",
        "P5",
        "P1",
        "P2",
        "P6",
        "PO7",
        "PO3",
        "POz",
        "PO8"
      ]
    },
    "markers": {
      "has_events_tsv": false,
      "n_bids_events": 0,
      "unique_event_types": [],
      "eo_duration_sec": 0.0,
      "ec_duration_sec": 0.0,
      "annotation_count": 0,
      "annotation_events": [],
      "condition_from_filename": "eo"
    }
  },
  "pre_ec": {
    "integrity": {
      "sfreq": 1000.0,
      "n_channels": 64,
      "duration_sec": 185.0,
      "duration_min": 3.08,
      "median_abs_amplitude_uv": 62.86
    },
    "channels": {
      "n_eeg_channels": 64,
      "present_19": [
        "Fp1",
        "Fp2",
        "F7",
        "F3",
        "Fz",
        "F4",
        "F8",
        "T3",
        "C3",
        "Cz",
        "C4",
        "T4",
        "T5",
        "P3",
        "Pz",
        "P4",
        "T6",
        "O1",
        "O2"
      ],
      "missing_19": [],
      "additional_1010": [
        "AF3",
        "AF4",
        "AF7",
        "AF8",
        "C1",
        "C2",
        "C5",
        "C6",
        "CP1",
        "CP2",
        "CP3",
        "CP4",
        "CP5",
        "CP6",
        "CPz",
        "F1",
        "F2",
        "F5",
        "F6",
        "FC1",
        "FC2",
        "FC3",
        "FC4",
        "FC5",
        "FC6",
        "FT10",
        "FT7",
        "FT8",
        "FT9",
        "Oz",
        "P1",
        "P2",
        "P5",
        "P6",
        "PO10",
        "PO3",
        "PO4",
        "PO7",
        "PO8",
        "PO9",
        "POz",
        "TP10",
        "TP7",
        "TP8",
        "TP9"
      ],
      "fcz_present": false,
      "fcz_variance_uv2": null,
      "flat_channels": [],
      "railed_channels": [
        "TP9"
      ],
      "noisy_50hz_channels": []
    },
    "signal_quality": {
      "median_amplitude_uv": 62.86,
      "per_channel_median_uv": {
        "Fp1": 54.59,
        "Fp2": 58.01,
        "F7": 37.59,
        "F3": 59.99,
        "Fz": 49.25,
        "F4": 78.89,
        "F8": 70.8,
        "FC5": 91.01,
        "FC1": 36.19,
        "FC2": 141.34,
        "FC6": 22.32,
        "T7": 59.55,
        "C3": 72.03,
        "Cz": 58.35,
        "C4": 104.64,
        "T8": 42.22,
        "TP9": 555.94,
        "CP5": 153.64,
        "CP1": 94.14,
        "CP2": 165.81,
        "CP6": 135.34,
        "TP10": 134.51,
        "P7": 78.43,
        "P3": 55.88,
        "Pz": 86.09,
        "P4": 143.48,
        "P8": 149.56,
        "PO9": 35.03,
        "O1": 103.37,
        "Oz": 31.16,
        "O2": 19.55,
        "PO10": 22.67,
        "AF7": 90.9,
        "AF3": 33.22,
        "AF4": 21.98,
        "AF8": 142.33,
        "F5": 33.24,
        "F1": 20.64,
        "F2": 35.67,
        "F6": 51.42,
        "FT9": 114.01,
        "FT7": 94.29,
        "FC3": 115.34,
        "FC4": 135.99,
        "FT8": 119.02,
        "FT10": 44.25,
        "C5": 98.55,
        "C1": 46.46,
        "C2": 74.57,
        "C6": 104.96,
        "TP7": 229.04,
        "CP3": 72.86,
        "CPz": 102.95,
        "CP4": 11.32,
        "TP8": 36.91,
        "P5": 204.72,
        "P1": 249.8,
        "P2": 50.41,
        "P6": 57.79,
        "PO7": 73.84,
        "PO3": 47.72,
        "POz": 30.77,
        "PO4": 21.2,
        "PO8": 184.84
      },
      "gross_artifact_pct": 0.54,
      "n_artifact_epochs": 1,
      "n_total_epochs": 185,
      "usable_duration_sec": 184.0,
      "dc_offsets_uv": {
        "Fp1": -189.91,
        "Fp2": 48.02,
        "F7": -217.44,
        "F3": -540.02,
        "Fz": -827.78,
        "F4": 346.39,
        "F8": -769.3,
        "FC5": -665.49,
        "FC1": -157.84,
        "FC2": 525.37,
        "FC6": -651.71,
        "T7": -672.95,
        "C3": -387.01,
        "Cz": -457.15,
        "C4": 476.4,
        "T8": -616.82,
        "TP9": 376.44,
        "CP5": -750.68,
        "CP1": -553.36,
        "CP2": -903.84,
        "CP6": -770.37,
        "TP10": -592.55,
        "P7": -243.93,
        "P3": -334.38,
        "Pz": -1024.95,
        "P4": 320.98,
        "P8": -1265.06,
        "PO9": -318.06,
        "O1": -917.87,
        "Oz": 45.34,
        "O2": -216.48,
        "PO10": -305.7,
        "AF7": -660.93,
        "AF3": 54.25,
        "AF4": -81.06,
        "AF8": 600.7,
        "F5": -116.74,
        "F1": -345.86,
        "F2": -286.17,
        "F6": -272.61,
        "FT9": -471.49,
        "FT7": -872.32,
        "FC3": -604.16,
        "FC4": 484.49,
        "FT8": -798.52,
        "FT10": -58.29,
        "C5": -520.95,
        "C1": -35.58,
        "C2": -526.46,
        "C6": -580.54,
        "TP7": -1700.46,
        "CP3": -641.64,
        "CPz": 485.55,
        "CP4": -38.36,
        "TP8": -90.12,
        "P5": 1128.76,
        "P1": 839.3,
        "P2": -637.09,
        "P6": 78.29,
        "PO7": -302.66,
        "PO3": -519.31,
        "POz": -295.27,
        "PO4": -214.3,
        "PO8": 1007.88
      },
      "channels_with_large_offset": [
        "Fp1",
        "F7",
        "F3",
        "Fz",
        "F4",
        "F8",
        "FC5",
        "FC1",
        "FC2",
        "FC6",
        "T7",
        "C3",
        "Cz",
        "C4",
        "T8",
        "TP9",
        "CP5",
        "CP1",
        "CP2",
        "CP6",
        "TP10",
        "P7",
        "P3",
        "Pz",
        "P4",
        "P8",
        "PO9",
        "O1",
        "O2",
        "PO10",
        "AF7",
        "AF8",
        "F5",
        "F1",
        "F2",
        "F6",
        "FT9",
        "FT7",
        "FC3",
        "FC4",
        "FT8",
        "C5",
        "C2",
        "C6",
        "TP7",
        "CP3",
        "CPz",
        "P5",
        "P1",
        "P2",
        "PO7",
        "PO3",
        "POz",
        "PO4",
        "PO8"
      ]
    },
    "markers": {
      "has_events_tsv": false,
      "n_bids_events": 0,
      "unique_event_types": [],
      "eo_duration_sec": 0.0,
      "ec_duration_sec": 0.0,
      "annotation_count": 0,
      "annotation_events": [],
      "condition_from_filename": "ec"
    }
  },
  "channel_mapping": {
    "mapping_1020": {
      "Fp1": "Fp1",
      "Fp2": "Fp2",
      "F7": "F7",
      "F3": "F3",
      "Fz": "Fz",
      "F4": "F4",
      "F8": "F8",
      "T3": "T7",
      "C3": "C3",
      "Cz": "Cz",
      "C4": "C4",
      "T4": "T8",
      "T5": "P7",
      "P3": "P3",
      "Pz": "Pz",
      "P4": "P4",
      "T6": "P8",
      "O1": "O1",
      "O2": "O2"
    },
    "present_19": [
      "Fp1",
      "Fp2",
      "F7",
      "F3",
      "Fz",
      "F4",
      "F8",
      "T3",
      "C3",
      "Cz",
      "C4",
      "T4",
      "T5",
      "P3",
      "Pz",
      "P4",
      "T6",
      "O1",
      "O2"
    ],
    "missing_19": [],
    "additional_1010": [
      "AF3",
      "AF4",
      "AF7",
      "AF8",
      "C1",
      "C2",
      "C5",
      "C6",
      "CP1",
      "CP2",
      "CP3",
      "CP4",
      "CP5",
      "CP6",
      "CPz",
      "F1",
      "F2",
      "F5",
      "F6",
      "FC1",
      "FC2",
      "FC3",
      "FC4",
      "FC5",
      "FC6",
      "FT10",
      "FT7",
      "FT8",
      "FT9",
      "Oz",
      "P1",
      "P2",
      "P5",
      "P6",
      "PO10",
      "PO3",
      "PO4",
      "PO7",
      "PO8",
      "PO9",
      "POz",
      "TP10",
      "TP7",
      "TP8",
      "TP9"
    ]
  }
}